margot/__init__.py
margot/__main__.py
margot/_version.py
margot/config/__init__.py
margot/config/settings.py
margot/data/__init__.py
margot/data/alphavantage.py
margot/data/cboe.py
margot/data/columns.py
margot/data/frames.py
margot/data/ratio.py
margot/data/symbols.py
margot/data/features/__init__.py
margot/data/features/finance.py
margot/portfolio/__init__.py
margot/portfolio/portfolio.py
margot/signals/__init__.py
margot/signals/algos.py
margot/signals/backtest.py
margot/signals/order_types.py
margot/signals/periods.py
margot/tests/__init__.py
margot/tests/test_backtest.py
margot/tests/test_data.py
margot/tests/test_signals.py
margot/tools/__init__.py
margot/tools/ftxtools.py
margot/tools/gcptools.py
margot/trade/__init__.py
margot/trade/algos.py
margot/trade/calibrate.py
margot/trade/ibkr.py
margot/trade/manager.py
margot/trade/scheduler.py
margot/trade/server.py
margot/trade/worker.py
margot-1.13.dist-info/LICENSE
margot-1.13.dist-info/METADATA
margot-1.13.dist-info/WHEEL
margot-1.13.dist-info/top_level.txt
margot-1.13.dist-info/RECORD
