Metadata-Version: 2.1
Name: margot
Version: 1.13
Summary: An algorithmic trading framework for PyData.
Home-page: https://github.com/pymargot/margot
Author: Rich Atkinson
Author-email: rich@airteam.com.au
License: apache-2.0
Keywords: quant,trading,systematic
Platform: UNKNOWN
Classifier: Development Status :: 3 - Alpha
Classifier: Intended Audience :: Developers
Classifier: Topic :: Software Development :: Libraries :: Python Modules
Classifier: License :: OSI Approved :: Apache Software License
Classifier: Programming Language :: Python :: 3
Classifier: Programming Language :: Python :: 3.6
Classifier: Programming Language :: Python :: 3.7
Classifier: Programming Language :: Python :: 3.8
Requires-Dist: alpha-vantage
Requires-Dist: exchange-calendars
Requires-Dist: ftx
Requires-Dist: numpy
Requires-Dist: pandas
Requires-Dist: pyfolio
Requires-Dist: pytz
Requires-Dist: scipy
Requires-Dist: tables
Requires-Dist: versioneer
